pdfread/__init__.py
pdfread/document.pdf
pdfread/extracter.py
pdfread/pdfread.py
pdfread-0.1.1.dist-info/METADATA
pdfread-0.1.1.dist-info/WHEEL
pdfread-0.1.1.dist-info/entry_points.txt
pdfread-0.1.1.dist-info/RECORD
