Metadata-Version: 2.1
Name: pdfread
Version: 0.1.1
Summary: Invision I Terminal PDF Reader
Author: Arghya Sarkar
Author-email: arghyasarkar.nolan@gmail.com
Requires-Python: >=3.9,<4.0
Classifier: Programming Language :: Python :: 3
Classifier: Programming Language :: Python :: 3.9
Classifier: Programming Language :: Python :: 3.10
Classifier: Programming Language :: Python :: 3.11
Classifier: Programming Language :: Python :: 3.12
Requires-Dist: click (>=8.1.7,<9.0.0)
Requires-Dist: pymupdf (>=1.23.7,<2.0.0)
Requires-Dist: pytesseract (>=0.3.10,<0.4.0)
